sanic_healthchecks/__init__.py
sanic_healthchecks/core.py
sanic_healthchecks-1.0.1.dist-info/LICENSE
sanic_healthchecks-1.0.1.dist-info/WHEEL
sanic_healthchecks-1.0.1.dist-info/METADATA
sanic_healthchecks-1.0.1.dist-info/RECORD
