Metadata-Version: 2.1
Name: sanic-healthchecks
Version: 1.0.1
Summary: A small wrapper for making it easy to add a healthcheck server to your Sanic application
Home-page: https://github.com/abatilo/sanic-healthchecks
Keywords: sanic,health,checks,healthchecks,observability
Author: Aaron
Author-email: AaronBatilo@gmail.com
Requires-Python: >=3.7,<4.0
Classifier: Development Status :: 5 - Production/Stable
Classifier: Intended Audience :: Developers
Classifier: License :: OSI Approved :: Apache Software License
Classifier: Programming Language :: Python :: 3
Classifier: Programming Language :: Python :: 3.7
Classifier: Topic :: Software Development :: Libraries :: Python Modules
Requires-Dist: aiohttp (>=3.5,<4.0)
Project-URL: Repository, https://github.com/abatilo/sanic-healthchecks
